{
    "levelTime" : 20,
    "levelText": "LEVEL 1",
    "playerShip": {
        "key": "ship1Animation",
        "health": 100,
        "speed": 200,
        "playerDamageToEnemyShip":10
    },
    "enemyShipSpawnTime":5,
    "enemyShipCount": 3,
    "enemyShips": [
        {  
            "x": 300,
            "y": 40,
            "key":  "stingray",
            "frame": 0,
            "enemyHealth": 20,
            "enemyHealthDamage":10,
            "enemyDamageToPlayerShip": 5,
            "speed": 50,
            "firingTime": 2,
            "type": "easy"
        },
        { 
            "x": 590,
            "y": 30,
            "key":  "otter",
            "frame": 0,
            "enemyHealth": 20,
            "enemyHealthDamage":10,
            "enemyDamageToPlayerShip": 5,
            "speed": 150,
            "firingTime": 10,
            "type": "easy"
        },
        {
            "x": 120,
            "y": 432,
            "key":  "crab",
            "frame": 0,
            "enemyHealth": 100,
            "enemyHealthDamage":25,
            "enemyDamageToPlayerShip": 5,
            "speed": 100,
            "firingTime": 5,
            "type": "medium"
        }
    ],
    "islands":[
        {
            "x": 550,
            "y": 200,
            "key":  "island7",
            "frame": 0
        },
        {
            "x": 150,
            "y": 100,
            "key":  "island9",
            "frame": 0
        },
        {
            "x": 850,
            "y": 50,
            "key":  "island8",
            "frame": 0
        },
        {
            "x": 180,
            "y": 450,
            "key":  "island5",
            "frame": 0
        },
        {
            "x": 1000,
            "y": 400,
            "key":  "island8",
            "frame": 0
        }

    ],
    "powerUpSpawnTime": 50,
    "powerUps":[
        {
            "label": "PlayerLife",
            "sprite": "heart",
            "value": 10,
            "time": "0"
        },
        {   
            "label": "Invisible",
            "sprite": "invisible",
            "value": 0.3,
            "time": "10"
        },
        {   
            "label": "Mine",
            "sprite": "mine",
            "value": 70,
            "time": "0"
        },
        {   
            "label": "PlayerFast",
            "sprite": "speedFastPlayer",
            "value": 1200,
            "time": "10"
        },
        {   
            "label": "PlayerSlow",
            "sprite": "speedSlowPlayer",
            "value": 100,
            "time": "10"
        },
        {   
            "label": "EnemySlow",
            "sprite": "speedSlowEnemy",
            "value": 10,
            "time": "10"
        },
        {   
            "label": "EnemyFast",
            "sprite": "speedFastEnemy",
            "value": 200,
            "time": "10"
        },
        {   
            "label": "PlayerGrow",
            "sprite": "growPlayer",
            "value": 0.5,
            "time": "10"
        }

        
    ]
}